__init__.py
check.py
bluefin_v2_client/__init__.py
bluefin_v2_client/account.py
bluefin_v2_client/api_service.py
bluefin_v2_client/client.py
bluefin_v2_client/constants.py
bluefin_v2_client/contracts.py
bluefin_v2_client/enumerations.py
bluefin_v2_client/interfaces.py
bluefin_v2_client/onboarding_signer.py
bluefin_v2_client/order_signer.py
bluefin_v2_client/rpc.py
bluefin_v2_client/signer.py
bluefin_v2_client/socket_manager.py
bluefin_v2_client/sockets_lib.py
bluefin_v2_client/utilities.py
bluefin_v2_client/websocket_client.py
bluefin_v2_client-4.2.13.dist-info/LICENSE
bluefin_v2_client-4.2.13.dist-info/METADATA
bluefin_v2_client-4.2.13.dist-info/WHEEL
bluefin_v2_client-4.2.13.dist-info/top_level.txt
bluefin_v2_client-4.2.13.dist-info/RECORD
